structgen/__init__.py
structgen/cli.py
structgen/constants.py
structgen/utils.py
structgen/handlers/__init__.py
structgen/handlers/atomic.py
structgen/handlers/charge.py
structgen/handlers/full_devel.py
structgen/handlers/molecular_devel.py
lammps_structgen-0.1.6.dist-info/METADATA
lammps_structgen-0.1.6.dist-info/WHEEL
lammps_structgen-0.1.6.dist-info/entry_points.txt
lammps_structgen-0.1.6.dist-info/licenses/LICENSE
lammps_structgen-0.1.6.dist-info/RECORD
