Metadata-Version: 2.4
Name: lammps-structgen
Version: 0.1.6
Summary: Generator for LAMMPS initial atomic structures for glassy systems.
Project-URL: Homepage, https://github.com/superde1fin/structgen
Project-URL: Source, https://github.com/superde1fin/structgen
Project-URL: Issues, https://github.com/superde1fin/structgen/issues
License: GPL-3.0-only
License-File: LICENSE
Requires-Python: >=3.9
Provides-Extra: dev
Requires-Dist: build>=1.2; extra == 'dev'
Requires-Dist: mypy>=1.10; extra == 'dev'
Requires-Dist: pytest>=8.1; extra == 'dev'
Requires-Dist: ruff>=0.4; extra == 'dev'
Requires-Dist: twine>=5.0; extra == 'dev'
